{
  "metrics": {
    "totalUsers": 15240,
    "activeSessions": 345,
    "revenue": "$124,560"
  },
  "activity": [120, 200, 180, 240, 300, 400, 350],
  "users": [
    { "name": "Alice Johnson", "email": "alice.johnson@techwizz.com", "date": "2024-11-20" },
    { "name": "Bob Smith", "email": "bob.smith@techwizz.com", "date": "2024-11-19" },
    { "name": "Carlos Martinez", "email": "carlos.martinez@techwizz.com", "date": "2024-11-18" },
    { "name": "Diana Prince", "email": "diana.prince@techwizz.com", "date": "2024-11-17" },
    { "name": "Ethan Brown", "email": "ethan.brown@techwizz.com", "date": "2024-11-16" },
    { "name": "Fiona Davis", "email": "fiona.davis@techwizz.com", "date": "2024-11-15" },
    { "name": "George Wilson", "email": "george.wilson@techwizz.com", "date": "2024-11-14" },
    { "name": "Hannah Taylor", "email": "hannah.taylor@techwizz.com", "date": "2024-11-13" },
    { "name": "Ian Wright", "email": "ian.wright@techwizz.com", "date": "2024-11-12" },
    { "name": "Jessica Lee", "email": "jessica.lee@techwizz.com", "date": "2024-11-11" },
    { "name": "Kevin Moore", "email": "kevin.moore@techwizz.com", "date": "2024-11-10" },
    { "name": "Laura Adams", "email": "laura.adams@techwizz.com", "date": "2024-11-09" },
    { "name": "Michael Scott", "email": "michael.scott@techwizz.com", "date": "2024-11-08" },
    { "name": "Nina Roberts", "email": "nina.roberts@techwizz.com", "date": "2024-11-07" },
    { "name": "Oscar Peterson", "email": "oscar.peterson@techwizz.com", "date": "2024-11-06" },
    { "name": "Patricia Campbell", "email": "patricia.campbell@techwizz.com", "date": "2024-11-05" },
    { "name": "Quincy Baker", "email": "quincy.baker@techwizz.com", "date": "2024-11-04" },
    { "name": "Rachel Carter", "email": "rachel.carter@techwizz.com", "date": "2024-11-03" },
    { "name": "Samuel Harris", "email": "samuel.harris@techwizz.com", "date": "2024-11-02" },
    { "name": "Tina Gomez", "email": "tina.gomez@techwizz.com", "date": "2024-11-01" }
  ]
}
